<annotation>
	<folder>Img_avec_eolienne</folder>
	<filename>img_119_W.png</filename>
	<path>C:\Users\JP\Documents\Mines\S2\Projet Info\Code J Bressan\Img eoliennes\Img_avec_eolienne\img_119_W.png</path>
	<source>
		<database>Unknown</database>
	</source>
	<size>
		<width>512</width>
		<height>512</height>
		<depth>3</depth>
	</size>
	<segmented>0</segmented>
	<object>
		<name>wt</name>
		<pose>Unspecified</pose>
		<truncated>0</truncated>
		<difficult>0</difficult>
		<bndbox>
			<xmin>270</xmin>
			<ymin>196</ymin>
			<xmax>319</xmax>
			<ymax>267</ymax>
		</bndbox>
	</object>
</annotation>
