<annotation>
	<folder>Img_avec_eolienne</folder>
	<filename>img_104_E.png</filename>
	<path>C:\Users\JP\Documents\Mines\S2\Projet Info\Code J Bressan\Img eoliennes\Img_avec_eolienne\img_104_E.png</path>
	<source>
		<database>Unknown</database>
	</source>
	<size>
		<width>512</width>
		<height>512</height>
		<depth>3</depth>
	</size>
	<segmented>0</segmented>
	<object>
		<name>wt</name>
		<pose>Unspecified</pose>
		<truncated>0</truncated>
		<difficult>0</difficult>
		<bndbox>
			<xmin>174</xmin>
			<ymin>137</ymin>
			<xmax>231</xmax>
			<ymax>268</ymax>
		</bndbox>
	</object>
	<object>
		<name>wt</name>
		<pose>Unspecified</pose>
		<truncated>0</truncated>
		<difficult>0</difficult>
		<bndbox>
			<xmin>316</xmin>
			<ymin>4</ymin>
			<xmax>365</xmax>
			<ymax>80</ymax>
		</bndbox>
	</object>
	<object>
		<name>wt</name>
		<pose>Unspecified</pose>
		<truncated>0</truncated>
		<difficult>0</difficult>
		<bndbox>
			<xmin>430</xmin>
			<ymin>130</ymin>
			<xmax>500</xmax>
			<ymax>264</ymax>
		</bndbox>
	</object>
</annotation>
